task1/rom.sv
module rom #(
    parameter   ADDRESS_WIDTH = 8,
                DATA_WIDTH = 8
)(
    input logic     clk,         // input clock
    input logic[ADDRESS_WIDTH-1:0]     addr,     // serial data in
    output logic[DATA_WIDTH-1:0]     dout    // serial data out
);

    logic [DATA_WIDTH-1:0] rom_array [2**ADDRESS_WIDTH-1:0];

    initial begin
            $display("Loading rom");
            $readmemh("sinerom.mem", rom_array);
    end;

    always_ff @(posedge clk)
        dout <= rom_array[addr];
        
endmodule

task2/counter.sv
module counter#(
  parameter WIDTH = 8
)(
  // interface signals
  input  logic             clk,      // clock
  input  logic             rst,      // reset
  input  logic             en,       // load counter from data
  input  logic [WIDTH-1:0] incr,     // value to preload
  output logic [WIDTH-1:0] dout     // count output
);

always_ff @ (posedge clk)
  if (rst) dout <= {WIDTH{1'b0}};
  else     dout <= dout + incr;

endmodule

task2/sinegen.sv
module sinegen #(
    parameter   A_WIDTH = 8,
                D_WIDTH = 8
)(
    input logic clk,         // clock
    input logic rst,         // reset trigger
    input logic en,          // counter enable
    input logic [D_WIDTH-1:0] incr,
    output logic [D_WIDTH-1:0] data_out   // output   
);

    logic [A_WIDTH-1:0] addr;
    
counter myCounter (
    .incr (incr),
    .rst (rst),
    .en (en),
    .clk (clk),
    .dout (addr)
);

rom myRom (
    .clk (clk),
    .addr (addr),
    .dout (data_out)
);

endmodule

task1/sinegen.vcd
$version Generated by VerilatedVcd $end
$date Wed Oct 23 19:22:48 2024 $end
$timescale 1ps $end

 $scope module TOP $end
  $var wire  1 # clk $end
  $var wire  8 ' data_out [7:0] $end
  $var wire  1 % en $end
  $var wire  8 & incr [7:0] $end
  $var wire  1 $ rst $end
  $scope module sinegen $end
   $var wire 32 ) A_WIDTH [31:0] $end
   $var wire 32 ) D_WIDTH [31:0] $end
   $var wire  8 ( addr [7:0] $end
   $var wire  1 # clk $end
   $var wire  8 ' data_out [7:0] $end
   $var wire  1 % en $end
   $var wire  8 & incr [7:0] $end
   $var wire  1 $ rst $end
   $scope module myCounter $end
    $var wire 32 ) WIDTH [31:0] $end
    $var wire  1 # clk $end
    $var wire  8 ( dout [7:0] $end
    $var wire  1 % en $end
    $var wire  8 & incr [7:0] $end
    $var wire  1 $ rst $end
   $upscope $end
   $scope module myRom $end
    $var wire 32 ) ADDRESS_WIDTH [31:0] $end
    $var wire 32 ) DATA_WIDTH [31:0] $end
    $var wire  8 ( addr [7:0] $end
    $var wire  1 # clk $end
    $var wire  8 ' dout [7:0] $end
   $upscope $end
  $upscope $end
 $upscope $end
$enddefinitions $end


#0
1#
0$
1%
b00000001 &
b00000000 '
b00000000 (
b00000000000000000000000000001000 )
#1
0#
#2
1#
b00100001 &
b11111110 '
b00000001 (
#3
0#
#4
1#
b11111101 '
b00100010 (
#5
0#
#6
1#
b11010100 '
b01000011 (
#7
0#
#8
1#
b01110101 '
b01100100 (
#9
0#
#10
1#
b00011100 '
b10000101 (
#11
0#
#12
1#
b00000000 '
b10100110 (
#13
0#
#14
1#
b00110011 '
b11000111 (
#15
0#
#16
1#
b10010100 '
b11101000 (
#17
0#
#18
1#
b11101000 '
b00001001 (
#19
0#
#20
1#
b11111010 '
b00101010 (
#21
0#
#22
1#
b11000000 '
b01001011 (
#23
0#
#24
1#
b01011101 '
b01101100 (
#25
0#
#26
1#
b00001110 '
b10001101 (
#27
0#
#28
1#
b00000110 '
b10101110 (
#29
0#
#30
1#
b01001000 '
b11001111 (
#31
0#
#32
1#
b10101100 '
b11110000 (
#33
0#
#34
1#
b11110100 '
b00010001 (
#35
0#
#36
1#
b11110011 '
b00110010 (
#37
0#
#38
1#
b10101001 '
b01010011 (
#39
0#
#40
1#
b01000101 '
b01110100 (
#41
0#
#42
1#
b00000101 '
b10010101 (
#43
0#
#44
1#
b00010000 '
b10110110 (
#45
0#
#46
1#
b01100000 '
b11010111 (
#47
0#
#48
1#
b11000010 '
b11111000 (
#49
0#
#50
1#
b11111011 '
b00011001 (
#51
0#
#52
1#
b11100110 '
b00111010 (
#53
0#
#54
1#
b10010001 '
b01011011 (
#55
0#
#56
1#
b00110000 '
b01111100 (
#57
0#
#58
1#
b00000000 '
b10011101 (
#59
0#
#60
1#
b00011110 '
b10111110 (
#61
0#
#62
1#
b01111000 '
b11011111 (
#63
0#
#64
1#
b11010110 '
b00000000 (
#65
0#
#66
1#
b11111110 '
b00100001 (
#67
0#
#68
1#
b11010110 '
b01000010 (
#69
0#
#70
1#
b01111000 '
b01100011 (
#71
0#
#72
1#
b00011110 '
b10000100 (
#73
0#
#74
1#
b00000000 '
b10100101 (
#75
0#
#76
1#
b00110000 '
b11000110 (
#77
0#
#78
1#
b10010001 '
b11100111 (
#79
0#
#80
1#
b11100110 '
b00001000 (
#81
0#
#82
1#
b11111011 '
b00101001 (
#83
0#
#84
1#
b11000010 '
b01001010 (
#85
0#
#86
1#
b01100000 '
b01101011 (
#87
0#
#88
1#
b00010000 '
b10001100 (
#89
0#
#90
1#
b00000101 '
b10101101 (
#91
0#
#92
1#
b01000101 '
b11001110 (
#93
0#
#94
1#
b10101001 '
b11101111 (
#95
0#
#96
1#
b11110011 '
b00010000 (
#97
0#
#98
1#
b11110100 '
b00110001 (
#99
0#
#100
1#
b10101100 '
b01010010 (
#101
0#
#102
1#
b01001000 '
b01110011 (
#103
0#
#104
1#
b00000110 '
b10010100 (
#105
0#
#106
1#
b00001110 '
b10110101 (
#107
0#
#108
1#
b01011101 '
b11010110 (
#109
0#
#110
1#
b11000000 '
b11110111 (
#111
0#
#112
1#
b11111010 '
b00011000 (
#113
0#
#114
1#
b11101000 '
b00111001 (
#115
0#
#116
1#
b10010100 '
b01011010 (
#117
0#
#118
1#
b00110011 '
b01111011 (
#119
0#
#120
1#
b00000000 '
b10011100 (
#121
0#
#122
1#
b00011100 '
b10111101 (
#123
0#
#124
1#
b01110101 '
b11011110 (
#125
0#
#126
1#
b11010100 '
b11111111 (
#127
0#
#128
1#
b11111101 '
b00100000 (
#129
0#
#130
1#
b11011000 '
b01000001 (
#131
0#
#132
1#
b01111011 '
b01100010 (
#133
0#
#134
1#
b00100000 '
b10000011 (
#135
0#
#136
1#
b00000000 '
b10100100 (
#137
0#
#138
1#
b00101110 '
b11000101 (
#139
0#
#140
1#
b10001110 '
b11100110 (
#141
0#
#142
1#
b00100000 &
b11100101 '
b00000111 (
#143
0#
#144
1#
b11111100 '
b00100111 (
#145
0#
#146
1#
b00011111 &
b11001000 '
b01000111 (
#147
0#
#148
1#
b01101001 '
b01100110 (
#149
0#
#150
1#
b00011000 '
b10000101 (
#151
0#
#152
1#
b00011110 &
b00000000 '
b10100100 (
#153
0#
#154
1#
b00101110 '
b11000010 (
#155
0#
#156
1#
b10000101 '
b11100000 (
#157
0#
#158
1#
b11011000 '
b11111110 (
#159
0#
#160
1#
b11111101 '
b00011100 (
#161
0#
#162
1#
b00011101 &
b11100001 '
b00111010 (
#163
0#
#164
1#
b10010001 '
b01010111 (
#165
0#
#166
1#
b00011100 &
b00111011 '
b01110100 (
#167
0#
#168
1#
b00011011 &
b00000101 '
b10010000 (
#169
0#
#170
1#
b00011010 &
b00001001 '
b10101011 (
#171
0#
#172
1#
b00011001 &
b01000000 '
b11000101 (
#173
0#
#174
1#
b00011000 &
b10001110 '
b11011110 (
#175
0#
#176
1#
b11010100 '
b11110110 (
#177
0#
#178
1#
b11111010 '
b00001110 (
#179
0#
#180
1#
b11110110 '
b00100110 (
#181
0#
#182
1#
b11001010 '
b00111110 (
#183
0#
#184
1#
b10000101 '
b01010110 (
#185
0#
#186
1#
b00111101 '
b01101110 (
#187
0#
#188
1#
b00001100 '
b10000110 (
#189
0#
#190
1#
b00000001 '
b10011110 (
#191
0#
#192
1#
b00100000 '
b10110110 (
#193
0#
#194
1#
b01100000 '
b11001110 (
#195
0#
#196
1#
b00010111 &
b10101001 '
b11100110 (
#197
0#
#198
1#
b00010100 &
b11100101 '
b11111101 (
#199
0#
#200
1#
b00010001 &
b11111101 '
b00010001 (
#201
0#
#202
1#
b00010000 &
b11110011 '
b00100010 (
#203
0#
#204
1#
b11010100 '
b00110010 (
#205
0#
#206
1#
b10101001 '
b01000010 (
#207
0#
#208
1#
b01111000 '
b01010010 (
#209
0#
#210
1#
b01001000 '
b01100010 (
#211
0#
#212
1#
b00100000 '
b01110010 (
#213
0#
#214
1#
b00000111 '
b10000010 (
#215
0#
#216
1#
b00000000 '
b10010010 (
#217
0#
#218
1#
b00001100 '
b10100010 (
#219
0#
#220
1#
b00101001 '
b10110010 (
#221
0#
#222
1#
b01010100 '
b11000010 (
#223
0#
#224
1#
b00001110 &
b10000101 '
b11010010 (
#225
0#
#226
1#
b00001011 &
b10110101 '
b11100000 (
#227
0#
#228
1#
b00001010 &
b11011000 '
b11101011 (
#229
0#
#230
1#
b00001000 &
b11101101 '
b11110101 (
#231
0#
#232
1#
b00000111 &
b11111001 '
b11111101 (
#233
0#
#234
1#
b11111101 '
b00000100 (
#235
0#
#236
1#
b00001011 (
#237
0#
#238
1#
b11111001 '
b00010010 (
#239
0#
#240
1#
b11110001 '
b00011001 (
#241
0#
#242
1#
b11100110 '
b00100000 (
#243
0#
#244
1#
b11011000 '
b00100111 (
#245
0#
#246
1#
b11001000 '
b00101110 (
#247
0#
#248
1#
b10110101 '
b00110101 (
#249
0#
#250
1#
b10100000 '
b00111100 (
#251
0#
#252
1#
b10001011 '
b01000011 (
#253
0#
#254
1#
b01110101 '
b01001010 (
#255
0#
#256
1#
b01100000 '
b01010001 (
#257
0#
#258
1#
b01001011 '
b01011000 (
#259
0#
#260
1#
b00000110 &
b00111000 '
b01011111 (
#261
0#
#262
1#
b00100111 '
b01100101 (
#263
0#
#264
1#
b00000101 &
b00011010 '
b01101011 (
#265
0#
#266
1#
b00010000 '
b01110000 (
#267
0#
#268
1#
b00001001 '
b01110101 (
#269
0#
#270
1#
b00000100 &
b00000100 '
b01111010 (
#271
0#
#272
1#
b00000001 '
b01111110 (
#273
0#
#274
1#
b00000000 '
b10000010 (
#275
0#
#276
1#
b00000011 &
b10000110 (
#277
0#
#278
1#
b00000001 '
b10001001 (
#279
0#
#280
1#
b00000010 &
b00000011 '
b10001100 (
#281
0#
#282
1#
b00000101 '
b10001110 (
#283
0#
#284
1#
b00000001 &
b00000111 '
b10010000 (
#285
0#
#286
1#
b00001001 '
b10010001 (
#287
0#
#288
1#
b00001010 '
b10010010 (
#289
0#
#290
1#
b00000000 &
b00001100 '
b10010011 (
#291
0#
#292
1#
b00001101 '
